README.md
license.txt
setup.py
glauco_automacao_teste_25.egg-info/PKG-INFO
glauco_automacao_teste_25.egg-info/SOURCES.txt
glauco_automacao_teste_25.egg-info/dependency_links.txt
glauco_automacao_teste_25.egg-info/top_level.txt
pro_video_ferramentas/__init__.py
pro_video_ferramentas/camera.py
pro_video_ferramentas/video.py