Metadata-Version: 2.4
Name: glauco-automacao-teste-25
Version: 1.0
Summary: Este pacote irá fornecer ferramentas de processamento de vídeo
Author: Glauco
Author-email: gvittibonturi@gmail.com
Keywords: camera,video,processamento
License-File: license.txt
Dynamic: author
Dynamic: author-email
Dynamic: description
Dynamic: keywords
Dynamic: license-file
Dynamic: summary
